[
    {
        "id": 1,
        "razaoSocial": "Cervejaria Campo Bom LTDA",
        "endereco": "Campo Bom - RS, Brasil",
        "coordenadas": {
            "longitude": -51.06552601,
            "latitude": -29.67756663
        }
    },
    {
        "id": 2,
        "razaoSocial": "Cervejaria Bohemia",
        "endereco": "Petrópolis - RJ, Brasil",
        "coordenadas": {
            "longitude": -43.184725,
            "latitude": -22.506295
        }
    },
    {
        "id": 3,
        "razaoSocial": "Gilde Brauerei",
        "endereco": "Hanôver - Baixa Saxónia, Alemanha",
        "coordenadas": {
            "longitude": -51.06552601,
            "latitude": -29.67756663
        }
    },
    {
        "id": 4,
        "razaoSocial": "Tupiniquim",
        "endereco": "Porto Alegre - RS, Brasil",
        "coordenadas": {
            "longitude": -51.06552601,
            "latitude": -29.67756663
        }
    },
    {
        "id": 5,
        "razaoSocial": "Santamate Indústria e Comércio LTDA",
        "endereco": "Santa Maria - RS, Brasil",
        "coordenadas": {
            "longitude": -53.783119,
            "latitude": -29.773929
        }
    }
]